aputils/__init__.py
aputils/__main__.py
aputils/enums.py
aputils/errors.py
aputils/message.py
aputils/misc.py
aputils/objects.py
aputils/py.typed
aputils/request_classes.py
aputils/signer.py
activitypub_utils-0.4.0.dist-info/LICENSE
activitypub_utils-0.4.0.dist-info/METADATA
activitypub_utils-0.4.0.dist-info/WHEEL
activitypub_utils-0.4.0.dist-info/top_level.txt
activitypub_utils-0.4.0.dist-info/RECORD
