Metadata-Version: 2.1
Name: activitypub-utils
Version: 0.4.0
Summary: Various classes and functions for ActivityPub servers
Author-email: Zoey Mae <admin@barkshark.xyz>
License:                     GNU GENERAL PUBLIC LICENSE
Project-URL: Homepage, https://codeberg.org/barkshark/aputils
Project-URL: Documentation, https://docs.barkshark.xyz/aputils
Keywords: python,activitypub,mastodon
Platform: any
Classifier: Development Status :: 4 - Beta
Classifier: Intended Audience :: Developers
Classifier: License :: OSI Approved :: GNU General Public License v3 or later (GPLv3+)
Classifier: Operating System :: OS Independent
Classifier: Programming Language :: Python
Classifier: Programming Language :: Python :: 3.10
Classifier: Programming Language :: Python :: 3.11
Classifier: Programming Language :: Python :: 3.12
Classifier: Programming Language :: Python :: 3.13
Classifier: Topic :: Software Development :: Libraries :: Python Modules
Classifier: Typing :: Typed
Requires-Python: >=3.10
License-File: LICENSE
Requires-Dist: barkshark-lib<0.3.0,>=0.2.3
Requires-Dist: pycryptodome==3.20.0
Provides-Extra: docs
Requires-Dist: furo==2024.1.29; extra == "docs"
Requires-Dist: sphinx==7.2.6; extra == "docs"
Requires-Dist: sphinx-external-toc==1.0.1; extra == "docs"
Provides-Extra: dev
Requires-Dist: mypy==1.10.1; extra == "dev"
Requires-Dist: flake8==7.1.0; extra == "dev"
Requires-Dist: typing_extensions>=4.10.0; python_version < "3.11.0" and extra == "dev"
Requires-Dist: types-aiofiles==24.1.0.20241221; extra == "dev"
Requires-Dist: types-requests==2.32.0.20241016; extra == "dev"
Requires-Dist: types-ujson==5.10.0.20240515; extra == "dev"
Requires-Dist: aiohttp>=3.11; extra == "dev"
Requires-Dist: flask>=3.1; extra == "dev"
Requires-Dist: requests>=2.32; extra == "dev"
Requires-Dist: sanic>=24.12; extra == "dev"
